mate_common/__init__.py
mate_common/assertions.py
mate_common/config.py
mate_common/error.py
mate_common/schemata.py
mate_common/state_machine.py
mate_common/utils.py
mate_common/datastructures/__init__.py
mate_common/datastructures/dict_utils.py
mate_common/datastructures/digraph.py
mate_common/datastructures/list_utils.py
mate_common/datastructures/priority_queue.py
mate_common/models/__init__.py
mate_common/models/analyses.py
mate_common/models/artifacts.py
mate_common/models/builds.py
mate_common/models/bytes.py
mate_common/models/challenge_broker.py
mate_common/models/compilations.py
mate_common/models/graphs.py
mate_common/models/integration.py
mate_common/models/manticore.py
mate_common/models/cpg_types/__init__.py
mate_common/models/cpg_types/bin.py
mate_common/models/cpg_types/dwarf.py
mate_common/models/cpg_types/intrinsics.py
mate_common/models/cpg_types/llvm.py
mate_common/models/cpg_types/mate.py
mate_common/models/cpg_types/mc.py
mate_common/schemata/edges.json
mate_common/schemata/endpoints.json
mate_common/schemata/nodes.json
mate_common/schemata/relationships.json
mate_common/schemata/signatures.json
mate_common-0.0.1.dist-info/METADATA
mate_common-0.0.1.dist-info/WHEEL
mate_common-0.0.1.dist-info/top_level.txt
mate_common-0.0.1.dist-info/RECORD
