Metadata-Version: 2.1
Name: mate-common
Version: 0.0.1
Summary: Shared models and utilities for MATE
Author: The MATE authors
Author-email: mate@galois.com
License: BSD-3-Clause
Project-URL: Documentation, https://mate.galois.com
Platform: any
Requires-Python: >=3.8
Requires-Dist: pydantic (~=1.9.0)
